knot0_schemas/__init__.py
knot0_schemas/validator.py
knot0_schemas-2.0.3.dist-info/METADATA
knot0_schemas-2.0.3.dist-info/WHEEL
knot0_schemas-2.0.3.dist-info/top_level.txt
knot0_schemas-2.0.3.dist-info/RECORD
