Metadata-Version: 2.4
Name: knot0-schemas
Version: 2.0.3
Summary: Knot0 JSON Schemas and validation (Python)
License: MIT
Project-URL: homepage, https://knot0.com
Requires-Python: >=3.9
Requires-Dist: jsonschema>=4.17.0
